floydnet/__init__.py
floydnet/functional.py
floydnet/transformer.py
floydnet-1.0.0.dist-info/METADATA
floydnet-1.0.0.dist-info/WHEEL
floydnet-1.0.0.dist-info/licenses/LICENSE
floydnet-1.0.0.dist-info/RECORD
