Metadata-Version: 2.4
Name: floydnet
Version: 1.0.0
Summary: Floyd Multi-Head Attention: a drop-in variant of PyTorch MHA with module and function APIs
Project-URL: Homepage, https://github.com/ocx-lab/FloydNet
Project-URL: Repository, https://github.com/ocx-lab/FloydNet
Project-URL: Issues, https://github.com/ocx-lab/FloydNet/issues
Author-email: Qiwei Ye <chivee.ye@gmail.com>
License:                                  Apache License
License-File: LICENSE
Keywords: attention,deep-learning,floydnet,multihead,pytorch,transformer
Classifier: Development Status :: 3 - Alpha
Classifier: Intended Audience :: Science/Research
Classifier: License :: OSI Approved :: MIT License
Classifier: Programming Language :: Python :: 3
Classifier: Programming Language :: Python :: 3 :: Only
Classifier: Programming Language :: Python :: 3.9
Classifier: Programming Language :: Python :: 3.10
Classifier: Programming Language :: Python :: 3.11
Classifier: Programming Language :: Python :: 3.12
Classifier: Topic :: Scientific/Engineering :: Artificial Intelligence
Requires-Python: >=3.9
Requires-Dist: torch>=2.1
Requires-Dist: typing-extensions>=4.6
Provides-Extra: dev
Requires-Dist: mypy>=1.8; extra == 'dev'
Requires-Dist: numpy>=1.24; extra == 'dev'
Requires-Dist: pytest-cov>=4.1; extra == 'dev'
Requires-Dist: pytest>=7.4; extra == 'dev'
Requires-Dist: ruff>=0.5; extra == 'dev'
